{"metadata":{},"options":{"plugins":[{"key":"base$1$0","visitor":{"_exploded":{},"_verified":{},"JSXNamespacedName":{"enter":[null]},"JSXElement":{"exit":[null]},"JSXFragment":{"exit":[null]},"Program":{"enter":[null],"exit":[null]},"JSXAttribute":{"enter":[null]}},"options":{"pragma":"React.createElement","pragmaFrag":"React.Fragment","throwIfNamespace":true,"useBuiltIns":false}},{"key":"base$1$1","visitor":{"_exploded":true,"_verified":true},"options":{}},{"key":"base$1$2","visitor":{"ExportDefaultDeclaration":{"enter":[null]},"CallExpression":{"enter":[null]},"_exploded":true,"_verified":true},"options":{}},{"key":"base$0$0","visitor":{"_exploded":true,"_verified":true},"options":{}},{"key":"base$0$1","visitor":{"_exploded":{},"_verified":{},"Program":{"enter":[null]},"ImportDeclaration":{"enter":[null,null]},"ClassProperty":{"enter":[null]},"AssignmentPattern":{"enter":[null]},"TypeCastExpression":{"enter":[null,null]},"ImportSpecifier":{"enter":[null]},"ClassDeclaration":{"enter":[null]},"ClassExpression":{"enter":[null]},"FunctionDeclaration":{"enter":[null]},"FunctionExpression":{"enter":[null]},"ObjectMethod":{"enter":[null]},"ArrowFunctionExpression":{"enter":[null]},"ClassMethod":{"enter":[null]},"AnyTypeAnnotation":{"enter":[null]},"ArrayTypeAnnotation":{"enter":[null]},"BooleanTypeAnnotation":{"enter":[null]},"BooleanLiteralTypeAnnotation":{"enter":[null]},"NullLiteralTypeAnnotation":{"enter":[null]},"ClassImplements":{"enter":[null]},"DeclareClass":{"enter":[null]},"DeclareFunction":{"enter":[null]},"DeclareInterface":{"enter":[null]},"DeclareModule":{"enter":[null]},"DeclareModuleExports":{"enter":[null]},"DeclareTypeAlias":{"enter":[null]},"DeclareOpaqueType":{"enter":[null]},"DeclareVariable":{"enter":[null]},"DeclareExportDeclaration":{"enter":[null]},"DeclareExportAllDeclaration":{"enter":[null]},"DeclaredPredicate":{"enter":[null]},"ExistsTypeAnnotation":{"enter":[null]},"FunctionTypeAnnotation":{"enter":[null]},"FunctionTypeParam":{"enter":[null]},"GenericTypeAnnotation":{"enter":[null]},"InferredPredicate":{"enter":[null]},"InterfaceExtends":{"enter":[null]},"InterfaceDeclaration":{"enter":[null]},"IntersectionTypeAnnotation":{"enter":[null]},"MixedTypeAnnotation":{"enter":[null]},"EmptyTypeAnnotation":{"enter":[null]},"NullableTypeAnnotation":{"enter":[null]},"NumberLiteralTypeAnnotation":{"enter":[null]},"NumberTypeAnnotation":{"enter":[null]},"ObjectTypeAnnotation":{"enter":[null]},"ObjectTypeCallProperty":{"enter":[null]},"ObjectTypeIndexer":{"enter":[null]},"ObjectTypeProperty":{"enter":[null]},"ObjectTypeSpreadProperty":{"enter":[null]},"OpaqueType":{"enter":[null]},"QualifiedTypeIdentifier":{"enter":[null]},"StringLiteralTypeAnnotation":{"enter":[null]},"StringTypeAnnotation":{"enter":[null]},"ThisTypeAnnotation":{"enter":[null]},"TupleTypeAnnotation":{"enter":[null]},"TypeofTypeAnnotation":{"enter":[null]},"TypeAlias":{"enter":[null]},"TypeAnnotation":{"enter":[null]},"TypeParameter":{"enter":[null]},"TypeParameterDeclaration":{"enter":[null]},"TypeParameterInstantiation":{"enter":[null]},"UnionTypeAnnotation":{"enter":[null]},"Variance":{"enter":[null]},"VoidTypeAnnotation":{"enter":[null]},"ExportAllDeclaration":{"enter":[null]},"ExportDefaultDeclaration":{"enter":[null]},"ExportNamedDeclaration":{"enter":[null]}},"options":{}},{"key":"base$0$2","visitor":{"CallExpression":{"enter":[null]},"BinaryExpression":{"enter":[null]},"MemberExpression":{"enter":[null],"exit":[null]},"_exploded":true,"_verified":true,"Identifier":{"enter":[null]},"JSXIdentifier":{"enter":[null]}},"options":{"polyfill":false,"useBuiltIns":true}},{"key":"base$0$3","visitor":{"_exploded":true,"_verified":true,"BlockStatement":{"enter":[null]},"CatchClause":{"enter":[null]},"DoWhileStatement":{"enter":[null]},"ForInStatement":{"enter":[null]},"ForStatement":{"enter":[null]},"FunctionDeclaration":{"enter":[null]},"FunctionExpression":{"enter":[null]},"Program":{"enter":[null]},"ObjectMethod":{"enter":[null]},"SwitchStatement":{"enter":[null]},"WhileStatement":{"enter":[null]},"ArrowFunctionExpression":{"enter":[null]},"ClassDeclaration":{"enter":[null]},"ClassExpression":{"enter":[null]},"ForOfStatement":{"enter":[null]},"ClassMethod":{"enter":[null]}},"options":{}},{"key":"base$0$4","visitor":{"_exploded":true,"_verified":true},"options":{}},{"key":"base$0$5","visitor":{"_exploded":{},"_verified":{},"VariableDeclarator":{"enter":[null]},"ExportNamedDeclaration":{"enter":[null]},"CatchClause":{"enter":[null]},"AssignmentExpression":{"enter":[null]},"ObjectExpression":{"enter":[null]},"FunctionDeclaration":{"enter":[null]},"FunctionExpression":{"enter":[null]},"ObjectMethod":{"enter":[null]},"ArrowFunctionExpression":{"enter":[null]},"ClassMethod":{"enter":[null]},"ForInStatement":{"enter":[null]},"ForOfStatement":{"enter":[null]}},"options":{}},{"key":"transform-meteor-async-await","visitor":{"AwaitExpression":{"enter":[null]},"_exploded":true,"_verified":true,"FunctionDeclaration":{"exit":[null]},"FunctionExpression":{"exit":[null]},"ObjectMethod":{"exit":[null]},"ArrowFunctionExpression":{"exit":[null]},"ClassMethod":{"exit":[null]}},"options":{"useNativeAsyncAwait":false}},{"key":"transform-meteor-dynamic-import","visitor":{"_exploded":{},"_verified":{},"CallExpression":{"enter":[null]}},"options":{}},{"key":"base$0$8","visitor":{"_exploded":{},"_verified":{},"ClassDeclaration":{"enter":[null]},"ClassExpression":{"enter":[null]}},"options":{}},{"key":"base$0$9","visitor":{"_exploded":{},"_verified":{},"FunctionDeclaration":{"enter":[null]},"FunctionExpression":{"enter":[null]},"ObjectMethod":{"enter":[null]},"ArrowFunctionExpression":{"enter":[null]},"ClassMethod":{"enter":[null]}},"options":{}},{"key":"base$0$10","visitor":{"Program":{"enter":[null]},"_exploded":true,"_verified":true},"options":{"generateLetDeclarations":true,"enforceStrictMode":false}}],"compact":false,"ast":true,"babelrc":false,"sourceFileName":"imports/ui/App.js","filename":"imports/ui/App.js","sourceMapTarget":"imports/ui/App.js.map","sourceMaps":true,"presets":[],"passPerPreset":false,"envName":"development","cwd":"/Users/taiwotejuosho/taiwo-do","parserOpts":{"sourceType":"module","sourceFileName":"imports/ui/App.js","plugins":["jsx","jsx","flow","flow","objectRestSpread","objectRestSpread","dynamicImport","classProperties","asyncGenerators"]},"generatorOpts":{"filename":"imports/ui/App.js","comments":true,"compact":false,"sourceMaps":true,"sourceMapTarget":"imports/ui/App.js.map","sourceFileName":"imports/ui/App.js"}},"code":"let React, Component;\nmodule.watch(require(\"react\"), {\n  default(v) {\n    React = v;\n  },\n\n  Component(v) {\n    Component = v;\n  }\n\n}, 0);\nlet withTracker;\nmodule.watch(require(\"meteor/react-meteor-data\"), {\n  withTracker(v) {\n    withTracker = v;\n  }\n\n}, 1);\nlet Tasks;\nmodule.watch(require(\"../api/tasks.js\"), {\n  Tasks(v) {\n    Tasks = v;\n  }\n\n}, 2);\nlet Task;\nmodule.watch(require(\"./Task.js\"), {\n  default(v) {\n    Task = v;\n  }\n\n}, 3);\n\n// App component - represents the whole app\nclass App extends Component {\n  renderTasks() {\n    return this.props.tasks.map(task => React.createElement(Task, {\n      key: task._id,\n      task: task\n    }));\n  }\n\n  render() {\n    return React.createElement(\"div\", {\n      className: \"container\"\n    }, React.createElement(\"header\", null, React.createElement(\"h1\", null, \"Todo List\"), React.createElement(\"form\", {\n      className: \"new-task\",\n      onSubmit: this.handleSubmit.bind(this)\n    }, React.createElement(\"input\", {\n      type: \"text\",\n      ref: \"textInput\",\n      placeholder: \"Type to add new tasks\"\n    }))), React.createElement(\"ul\", null, this.renderTasks()));\n  }\n\n}\n\nmodule.exportDefault(withTracker(() => {\n  return {\n    tasks: Tasks.find({}).fetch()\n  };\n})(App));","map":{"version":3,"sources":["imports/ui/App.js"],"names":["React","Component","module","watch","require","default","v","withTracker","Tasks","Task","App","renderTasks","props","tasks","map","task","_id","render","handleSubmit","bind","exportDefault","find","fetch"],"mappings":"AAAA,IAAIA,KAAJ,EAAUC,SAAV;AAAoBC,OAAOC,KAAP,CAAaC,QAAQ,OAAR,CAAb,EAA8B;AAACC,UAAQC,CAAR,EAAU;AAACN,YAAMM,CAAN;AAAQ,GAApB;;AAAqBL,YAAUK,CAAV,EAAY;AAACL,gBAAUK,CAAV;AAAY;;AAA9C,CAA9B,EAA8E,CAA9E;AAAiF,IAAIC,WAAJ;AAAgBL,OAAOC,KAAP,CAAaC,QAAQ,0BAAR,CAAb,EAAiD;AAACG,cAAYD,CAAZ,EAAc;AAACC,kBAAYD,CAAZ;AAAc;;AAA9B,CAAjD,EAAiF,CAAjF;AAAoF,IAAIE,KAAJ;AAAUN,OAAOC,KAAP,CAAaC,QAAQ,iBAAR,CAAb,EAAwC;AAACI,QAAMF,CAAN,EAAQ;AAACE,YAAMF,CAAN;AAAQ;;AAAlB,CAAxC,EAA4D,CAA5D;AAA+D,IAAIG,IAAJ;AAASP,OAAOC,KAAP,CAAaC,QAAQ,WAAR,CAAb,EAAkC;AAACC,UAAQC,CAAR,EAAU;AAACG,WAAKH,CAAL;AAAO;;AAAnB,CAAlC,EAAuD,CAAvD;;AAM3R;AACA,MAAMI,GAAN,SAAkBT,SAAlB,CAA4B;AAE1BU,gBAAc;AACZ,WAAO,KAAKC,KAAL,CAAWC,KAAX,CAAiBC,GAAjB,CAAsBC,IAAD,IAC1B,oBAAC,IAAD;AAAM,WAAKA,KAAKC,GAAhB;AAAqB,YAAMD;AAA3B,MADK,CAAP;AAGD;;AAEDE,WAAS;AACP,WACE;AAAK,iBAAU;AAAf,OACE,oCACE,4CADF,EAGE;AAAM,iBAAU,UAAhB;AAA2B,gBAAU,KAAKC,YAAL,CAAkBC,IAAlB,CAAuB,IAAvB;AAArC,OACE;AACE,YAAK,MADP;AAEE,WAAI,WAFN;AAGE,mBAAY;AAHd,MADF,CAHF,CADF,EAcE,gCACG,KAAKR,WAAL,EADH,CAdF,CADF;AAoBD;;AA7ByB;;AAP5BT,OAAOkB,aAAP,CAsCeb,YAAY,MAAM;AAC/B,SAAO;AACLM,WAAOL,MAAMa,IAAN,CAAW,EAAX,EAAeC,KAAf;AADF,GAAP;AAGD,CAJc,EAIZZ,GAJY,CAtCf","file":"imports/ui/App.js.map","sourcesContent":["import React, { Component } from 'react';\nimport { withTracker } from 'meteor/react-meteor-data';\n \nimport { Tasks } from '../api/tasks.js';\nimport Task from './Task.js';\n \n// App component - represents the whole app\nclass App extends Component {\n \n  renderTasks() {\n    return this.props.tasks.map((task) => (\n      <Task key={task._id} task={task} />\n    ));\n  }\n \n  render() {\n    return (\n      <div className=\"container\">\n        <header>\n          <h1>Todo List</h1>\n\n          <form className=\"new-task\" onSubmit={this.handleSubmit.bind(this)} >\n            <input\n              type=\"text\"\n              ref=\"textInput\"\n              placeholder=\"Type to add new tasks\"\n            />\n          </form>\n          \n        </header>\n \n        <ul>\n          {this.renderTasks()}\n        </ul>\n      </div>\n    );\n  }\n}\nexport default withTracker(() => {\n  return {\n    tasks: Tasks.find({}).fetch(),\n  };\n})(App);"]},"hash":"63cef8089e81784eb36e72cc6d136b87be00733e"}
